pagerduty_api/__init__.py
pagerduty_api/alerts.py
pagerduty_api/base.py
pagerduty_api/exceptions.py
pagerduty_api/version.py
pagerduty_api/tests/__init__.py
pagerduty_api/tests/alarm_tests.py
pagerduty_api/tests/base_tests.py
pagerduty_api-0.3.dist-info/DESCRIPTION.rst
pagerduty_api-0.3.dist-info/METADATA
pagerduty_api-0.3.dist-info/metadata.json
pagerduty_api-0.3.dist-info/RECORD
pagerduty_api-0.3.dist-info/top_level.txt
pagerduty_api-0.3.dist-info/WHEEL
