Metadata-Version: 2.0
Name: pagerduty-api
Version: 0.3
Summary: pagerduty-api is a package for easily interacting with PagerDuty's API.
Home-page: https://github.com/ambitioninc/pagerduty-api
Author: Micah Hausler
Author-email: opensource@ambition.com
License: MIT
Keywords: pagerduty,api,requests
Platform: UNKNOWN
Classifier: Programming Language :: Python :: 2.7
Classifier: Programming Language :: Python :: 3.3
Classifier: Programming Language :: Python :: 3.4
Classifier: Intended Audience :: Developers
Classifier: License :: OSI Approved :: MIT License
Classifier: Operating System :: OS Independent
Requires-Dist: requests (>=2.0.0)
